README.rst
setup.py
useresponse/__init__.py
useresponse/sso.py
useresponse.egg-info/PKG-INFO
useresponse.egg-info/SOURCES.txt
useresponse.egg-info/dependency_links.txt
useresponse.egg-info/requires.txt
useresponse.egg-info/top_level.txt
useresponse/api/__init__.py
useresponse/api/base.py
useresponse/api/comments.py
useresponse/api/exceptions.py
useresponse/api/objects.py
useresponse/api/tickets.py
useresponse/api/users.py