Metadata-Version: 2.1
Name: useresponse
Version: 0.0.7
Summary: Python client for Useresponse
Home-page: https://github.com/anxolerd/useresponse
Author: Oleksandr Kovalchuk
Author-email: anxolerd@outlook.com
License: MIT
Platform: UNKNOWN
Classifier: Development Status :: 1 - Planning
Classifier: Intended Audience :: Developers
Classifier: License :: OSI Approved :: MIT License
Classifier: Operating System :: OS Independent
Classifier: Programming Language :: Python
Classifier: Programming Language :: Python :: 3.6
Classifier: Programming Language :: Python :: 3.7
Classifier: Programming Language :: Python :: 3 :: Only
Classifier: Topic :: Software Development :: Libraries :: Python Modules
Requires-Python: >=3.6
